{"directed": true, "multigraph": false, "graph": {}, "nodes": [{"layer": 5, "feature": 23900, "explanation": "proper nouns related to individuals", "id": "5_23900"}, {"layer": 9, "feature": 24155, "explanation": "mentions of a person named \"Henrik\" in various contexts", "id": "9_24155"}, {"layer": 11, "feature": 16592, "explanation": "mention of the name \"Henrik\"", "id": "11_16592"}, {"layer": 3, "feature": 17290, "explanation": "proper names containing the syllable \"Hen\"", "id": "3_17290"}, {"layer": 7, "feature": 3465, "explanation": "proper nouns or personal names", "id": "7_3465"}, {"layer": 2, "feature": 20263, "explanation": "the name \"Henrik\"", "id": "2_20263"}, {"layer": 8, "feature": 7888, "explanation": "names of a specific person, \"Henrik\"", "id": "8_7888"}, {"layer": 4, "feature": 14960, "explanation": "the name \"Henrique\"", "id": "4_14960"}, {"layer": 10, "feature": 9585, "explanation": "names related to a specific individual", "id": "10_9585"}, {"layer": 0, "feature": 19538, "explanation": "proper nouns related to people or characters", "id": "0_19538"}, {"layer": 6, "feature": 588, "explanation": "names of specific individuals", "id": "6_588"}, {"layer": 1, "feature": 3284, "explanation": "mentions of the name \"Henrik\"", "id": "1_3284"}], "links": [{"similarity": 0.9402987957000732, "source": "5_23900", "target": "6_588"}, {"similarity": 0.9400230050086975, "source": "9_24155", "target": "10_9585"}, {"similarity": 0.9767056107521057, "source": "3_17290", "target": "4_14960"}, {"similarity": 0.96463942527771, "source": "7_3465", "target": "8_7888"}, {"similarity": 0.9767412543296814, "source": "2_20263", "target": "3_17290"}, {"similarity": 0.948036253452301, "source": "8_7888", "target": "9_24155"}, {"similarity": 0.9511846899986267, "source": "4_14960", "target": "5_23900"}, {"similarity": 0.935300350189209, "source": "10_9585", "target": "11_16592"}, {"similarity": 0.9656650424003601, "source": "0_19538", "target": "1_3284"}, {"similarity": 0.9553824067115784, "source": "6_588", "target": "7_3465"}, {"similarity": 0.9724042415618896, "source": "1_3284", "target": "2_20263"}]}