{"directed": true, "multigraph": false, "graph": {}, "nodes": [{"layer": 1, "feature": 20776, "explanation": "phrases related to the name \"Ki\" with different endings", "id": "1_20776"}, {"layer": 2, "feature": 19575, "explanation": "the name \"Kiwanuka\" and related mentions", "id": "2_19575"}, {"layer": 0, "feature": 11326, "explanation": "mentions of the name \"Kiwanguka\"", "id": "0_11326"}, {"layer": 5, "feature": 11064, "explanation": "names or terms related to the name \"Ki\"", "id": "5_11064"}, {"layer": 4, "feature": 23122, "explanation": "words or phrases that contain the name \"Ki\"", "id": "4_23122"}, {"layer": 3, "feature": 16775, "explanation": "phrases related to a specific person named 'Ki'", "id": "3_16775"}], "links": [{"similarity": 1.0, "source": "1_20776", "target": "2_19575"}, {"similarity": 1.0, "source": "2_19575", "target": "3_16775"}, {"similarity": 1.0, "source": "0_11326", "target": "1_20776"}, {"similarity": 0.8333333134651184, "source": "4_23122", "target": "5_11064"}, {"similarity": 0.8095238208770752, "source": "3_16775", "target": "4_23122"}]}