{"directed": true, "multigraph": false, "graph": {}, "nodes": [{"layer": 4, "feature": 16249, "explanation": "proper nouns related to names", "id": "4_16249"}, {"layer": 10, "feature": 6749, "explanation": "words related to encryption keys", "id": "10_6749"}, {"layer": 9, "feature": 8444, "explanation": "phrases related to key usage and security", "id": "9_8444"}, {"layer": 11, "feature": 19421, "explanation": "instances of encryption-related terms", "id": "11_19421"}, {"layer": 3, "feature": 2896, "explanation": "the word \"keys\" with a strong emphasis", "id": "3_2896"}, {"layer": 0, "feature": 16730, "explanation": "mentions of the word \"key\" often associated with names or technical use rather than the physical object", "id": "0_16730"}, {"layer": 3, "feature": 17302, "explanation": "phrases related to cryptographic keys and coding terms", "id": "3_17302"}, {"layer": 4, "feature": 6513, "explanation": "keywords related to physical objects or concepts of importance or significance", "id": "4_6513"}, {"layer": 4, "feature": 17365, "explanation": "key entities or components within a given context or system", "id": "4_17365"}, {"layer": 3, "feature": 23669, "explanation": "phrases or words related to the concept of importance or centrality", "id": "3_23669"}, {"layer": 0, "feature": 7272, "explanation": "key information or components within various contexts or topics appearing in the text", "id": "0_7272"}, {"layer": 5, "feature": 4592, "explanation": "keywords related to encryption and security keys", "id": "5_4592"}, {"layer": 2, "feature": 9307, "explanation": "the word \"keys\" along with their respective strength of association", "id": "2_9307"}, {"layer": 0, "feature": 7226, "explanation": "words related to the alcoholic beverage \"whiskeys.\"", "id": "0_7226"}, {"layer": 9, "feature": 3212, "explanation": "the word \"key.\"", "id": "9_3212"}, {"layer": 2, "feature": 18621, "explanation": "keywords or phrases related to cybersecurity or technology, specifically focusing on words containing 'key'", "id": "2_18621"}, {"layer": 1, "feature": 15205, "explanation": "words related to the name \"Key\"", "id": "1_15205"}, {"layer": 6, "feature": 14527, "explanation": "key concepts or important elements mentioned in various contexts", "id": "6_14527"}, {"layer": 7, "feature": 5657, "explanation": "key information or central points", "id": "7_5657"}, {"layer": 6, "feature": 505, "explanation": "keywords related to the term \"key\"", "id": "6_505"}, {"layer": 1, "feature": 17984, "explanation": "terms related to importance, significance, or central role", "id": "1_17984"}, {"layer": 2, "feature": 5929, "explanation": "terms related to a specific keyword \"Key\"", "id": "2_5929"}, {"layer": 8, "feature": 21068, "explanation": "keywords or main points within a sentence or text", "id": "8_21068"}, {"layer": 11, "feature": 10209, "explanation": "keywords or phrases that are important or central to a topic", "id": "11_10209"}, {"layer": 1, "feature": 19814, "explanation": "keywords or phrases related to physical keys", "id": "1_19814"}, {"layer": 0, "feature": 17546, "explanation": "keywords or key phrases", "id": "0_17546"}, {"layer": 5, "feature": 22481, "explanation": "words related to important or significant concepts or ideas", "id": "5_22481"}, {"layer": 3, "feature": 7193, "explanation": "keywords or names related to specific individuals or entities", "id": "3_7193"}, {"layer": 2, "feature": 23544, "explanation": "keywords or phrases denoting importance or significance", "id": "2_23544"}, {"layer": 10, "feature": 4596, "explanation": "phrases mentioning the concept of a \"key\" as a metaphor or symbol for something essential or crucial", "id": "10_4596"}, {"layer": 6, "feature": 11182, "explanation": "specific alphanumeric strings, likely related to cryptography or computer programming, particularly focusing on keywords or terms related to encryption keys", "id": "6_11182"}, {"layer": 1, "feature": 13065, "explanation": "words related to keys or specific locations", "id": "1_13065"}, {"layer": 0, "feature": 14229, "explanation": "specific identifiers, such as keys, within a document", "id": "0_14229"}, {"layer": 4, "feature": 7603, "explanation": "words related to encryption keys", "id": "4_7603"}, {"layer": 0, "feature": 18677, "explanation": "words related to keys, which could include literal keys as well as symbolic or metaphorical keys", "id": "0_18677"}, {"layer": 8, "feature": 17491, "explanation": "terms related to encryption and security keys", "id": "8_17491"}, {"layer": 7, "feature": 19323, "explanation": "terms related to encryption and security keys, as well as specific phrases mentioning key-related actions", "id": "7_19323"}, {"layer": 5, "feature": 2988, "explanation": "proper nouns", "id": "5_2988"}], "links": [{"similarity": 0.9456722140312195, "source": "4_16249", "target": "5_2988"}, {"similarity": 0.4739413559436798, "source": "4_16249", "target": "5_4592"}, {"similarity": 0.1581352800130844, "source": "10_6749", "target": "11_10209"}, {"similarity": 0.9334442615509033, "source": "10_6749", "target": "11_19421"}, {"similarity": 0.13804100453853607, "source": "9_8444", "target": "10_4596"}, {"similarity": 0.969239354133606, "source": "9_8444", "target": "10_6749"}, {"similarity": 0.9475982785224915, "source": "3_2896", "target": "4_6513"}, {"similarity": 0.6479820609092712, "source": "0_16730", "target": "1_15205"}, {"similarity": 0.9502796530723572, "source": "3_17302", "target": "4_7603"}, {"similarity": 0.46677929162979126, "source": "3_17302", "target": "4_16249"}, {"similarity": 0.19628514349460602, "source": "3_17302", "target": "4_17365"}, {"similarity": 0.12314978986978531, "source": "4_6513", "target": "5_4592"}, {"similarity": 0.20376630127429962, "source": "4_17365", "target": "5_4592"}, {"similarity": 0.9341040253639221, "source": "4_17365", "target": "5_22481"}, {"similarity": 0.21636545658111572, "source": "3_23669", "target": "4_7603"}, {"similarity": 0.9372822046279907, "source": "3_23669", "target": "4_17365"}, {"similarity": 0.9418254494667053, "source": "0_7272", "target": "1_17984"}, {"similarity": 0.47480106353759766, "source": "5_4592", "target": "6_505"}, {"similarity": 0.973099410533905, "source": "5_4592", "target": "6_11182"}, {"similarity": 0.1885090172290802, "source": "5_4592", "target": "6_14527"}, {"similarity": 0.7337883710861206, "source": "2_9307", "target": "3_2896"}, {"similarity": 0.11251503974199295, "source": "2_9307", "target": "3_17302"}, {"similarity": 0.2831050157546997, "source": "0_7226", "target": "1_19814"}, {"similarity": 0.8664987683296204, "source": "9_3212", "target": "10_4596"}, {"similarity": 0.1678321659564972, "source": "9_3212", "target": "10_6749"}, {"similarity": 0.808917224407196, "source": "2_18621", "target": "3_7193"}, {"similarity": 0.4625217914581299, "source": "2_18621", "target": "3_17302"}, {"similarity": 0.3317843973636627, "source": "1_15205", "target": "2_5929"}, {"similarity": 0.9327731132507324, "source": "1_15205", "target": "2_18621"}, {"similarity": 0.9292452931404114, "source": "6_14527", "target": "7_5657"}, {"similarity": 0.19774267077445984, "source": "6_14527", "target": "7_19323"}, {"similarity": 0.19091325998306274, "source": "7_5657", "target": "8_17491"}, {"similarity": 0.9196102023124695, "source": "7_5657", "target": "8_21068"}, {"similarity": 0.562666654586792, "source": "6_505", "target": "7_19323"}, {"similarity": 0.8354430198669434, "source": "1_17984", "target": "2_23544"}, {"similarity": 0.5028517246246338, "source": "2_5929", "target": "3_7193"}, {"similarity": 0.25074097514152527, "source": "2_5929", "target": "3_17302"}, {"similarity": 0.10363923758268356, "source": "2_5929", "target": "3_23669"}, {"similarity": 0.914893627166748, "source": "8_21068", "target": "9_3212"}, {"similarity": 0.16521738469600677, "source": "8_21068", "target": "9_8444"}, {"similarity": 0.7535211443901062, "source": "1_19814", "target": "2_9307"}, {"similarity": 0.6845018267631531, "source": "0_17546", "target": "1_13065"}, {"similarity": 0.37987011671066284, "source": "0_17546", "target": "1_15205"}, {"similarity": 0.2344127595424652, "source": "5_22481", "target": "6_11182"}, {"similarity": 0.8783482313156128, "source": "5_22481", "target": "6_14527"}, {"similarity": 0.47068771719932556, "source": "3_7193", "target": "4_7603"}, {"similarity": 0.9809160232543945, "source": "3_7193", "target": "4_16249"}, {"similarity": 0.12020201981067657, "source": "2_23544", "target": "3_7193"}, {"similarity": 0.3880747854709625, "source": "2_23544", "target": "3_17302"}, {"similarity": 0.6975772976875305, "source": "2_23544", "target": "3_23669"}, {"similarity": 0.8723667860031128, "source": "10_4596", "target": "11_10209"}, {"similarity": 0.12517130374908447, "source": "10_4596", "target": "11_19421"}, {"similarity": 0.1995215266942978, "source": "6_11182", "target": "7_5657"}, {"similarity": 0.8987069129943848, "source": "6_11182", "target": "7_19323"}, {"similarity": 0.9723756909370422, "source": "1_13065", "target": "2_5929"}, {"similarity": 0.3473108410835266, "source": "1_13065", "target": "2_18621"}, {"similarity": 0.1548343449831009, "source": "1_13065", "target": "2_23544"}, {"similarity": 0.7844036817550659, "source": "0_14229", "target": "1_19814"}, {"similarity": 0.4602648913860321, "source": "4_7603", "target": "5_2988"}, {"similarity": 0.9230313897132874, "source": "4_7603", "target": "5_4592"}, {"similarity": 0.2201005071401596, "source": "4_7603", "target": "5_22481"}, {"similarity": 0.30000001192092896, "source": "0_18677", "target": "1_13065"}, {"similarity": 0.17573800683021545, "source": "8_17491", "target": "9_3212"}, {"similarity": 0.9783573746681213, "source": "8_17491", "target": "9_8444"}, {"similarity": 0.9694656729698181, "source": "7_19323", "target": "8_17491"}, {"similarity": 0.17810086905956268, "source": "7_19323", "target": "8_21068"}, {"similarity": 0.9516128897666931, "source": "5_2988", "target": "6_505"}, {"similarity": 0.46899840235710144, "source": "5_2988", "target": "6_11182"}]}