{"directed": true, "multigraph": false, "graph": {}, "nodes": [{"layer": 5, "feature": 20969, "explanation": "proper nouns or entities, potentially related to data analysis or research", "id": "5_20969"}, {"layer": 1, "feature": 24039, "explanation": "mentions of various state governors", "id": "1_24039"}, {"layer": 0, "feature": 17959, "explanation": "government-related terms or mentions", "id": "0_17959"}, {"layer": 4, "feature": 24313, "explanation": "mentions of politicians with the title \"Governor\"", "id": "4_24313"}, {"layer": 5, "feature": 13788, "explanation": "mentions of government officials in news articles", "id": "5_13788"}, {"layer": 6, "feature": 15810, "explanation": "mentions of Governors", "id": "6_15810"}, {"layer": 7, "feature": 11254, "explanation": "mentions of state governors", "id": "7_11254"}, {"layer": 8, "feature": 20052, "explanation": "mentions of political figures who hold the title of Governor", "id": "8_20052"}, {"layer": 9, "feature": 20783, "explanation": "mentions of governmental figures", "id": "9_20783"}, {"layer": 10, "feature": 9656, "explanation": "mentions of governmental positions specifically related to state governors", "id": "10_9656"}, {"layer": 3, "feature": 3973, "explanation": "mentions of political figures holding the title of 'Governor'", "id": "3_3973"}, {"layer": 3, "feature": 8074, "explanation": "references to the term \"United\", likely associated with the name of a sports team such as Manchester United", "id": "3_8074"}, {"layer": 11, "feature": 22300, "explanation": "mentions of political figures who hold the title of Governor", "id": "11_22300"}, {"layer": 2, "feature": 13940, "explanation": "mentions of government officials or governors", "id": "2_13940"}, {"layer": 1, "feature": 6351, "explanation": "mentions of government-related terms", "id": "1_6351"}, {"layer": 4, "feature": 1271, "explanation": "names of organizations or entities with the word \"United.\"", "id": "4_1271"}, {"layer": 0, "feature": 15591, "explanation": "mentions of political figures holding the position of governor", "id": "0_15591"}], "links": [{"similarity": 0.14754098653793335, "source": "5_20969", "target": "6_15810"}, {"similarity": 0.75, "source": "1_24039", "target": "2_13940"}, {"similarity": 1.0, "source": "0_17959", "target": "1_6351"}, {"similarity": 0.9772727489471436, "source": "4_24313", "target": "5_13788"}, {"similarity": 0.13114753365516663, "source": "4_24313", "target": "5_20969"}, {"similarity": 1.0, "source": "5_13788", "target": "6_15810"}, {"similarity": 0.9090909361839294, "source": "6_15810", "target": "7_11254"}, {"similarity": 0.930232584476471, "source": "7_11254", "target": "8_20052"}, {"similarity": 0.6315789222717285, "source": "8_20052", "target": "9_20783"}, {"similarity": 0.699999988079071, "source": "9_20783", "target": "10_9656"}, {"similarity": 0.8947368264198303, "source": "10_9656", "target": "11_22300"}, {"similarity": 0.9772727489471436, "source": "3_3973", "target": "4_24313"}, {"similarity": 1.0, "source": "3_8074", "target": "4_1271"}, {"similarity": 1.0, "source": "2_13940", "target": "3_3973"}, {"similarity": 0.25, "source": "1_6351", "target": "2_13940"}, {"similarity": 0.23076923191547394, "source": "4_1271", "target": "5_20969"}, {"similarity": 0.25, "source": "0_15591", "target": "1_6351"}, {"similarity": 0.75, "source": "0_15591", "target": "1_24039"}]}