{"directed": true, "multigraph": false, "graph": {}, "nodes": [{"layer": 6, "feature": 23531, "explanation": "names or terms related to individuals, possibly linked to news, broadcasting, or personal life", "id": "6_23531"}, {"layer": 11, "feature": 5015, "explanation": "proper nouns related to different locations, potentially focusing on a specific region starting with the letter K", "id": "11_5015"}, {"layer": 7, "feature": 8901, "explanation": "the letter \"K\" followed by a single uppercase letter and a digit", "id": "7_8901"}, {"layer": 9, "feature": 19353, "explanation": "the letter \"K\" followed by a combination of other characters and numbers", "id": "9_19353"}, {"layer": 11, "feature": 15422, "explanation": "names starting with the letter \"K\"", "id": "11_15422"}, {"layer": 10, "feature": 11916, "explanation": "mentions of the letter \"K\" with accompanying numerical values", "id": "10_11916"}, {"layer": 0, "feature": 2368, "explanation": "proper nouns denoting specific names or terms", "id": "0_2368"}, {"layer": 11, "feature": 14795, "explanation": "mentions of the letter \"K\" followed by a number indicating a specific reference or ranking", "id": "11_14795"}, {"layer": 10, "feature": 17328, "explanation": "names with the initial \"K\" followed by a rating number", "id": "10_17328"}, {"layer": 5, "feature": 15445, "explanation": "capital letters 'K' followed by the number 9 or 10", "id": "5_15445"}, {"layer": 3, "feature": 3711, "explanation": "phrases related to the abbreviation \"K\" followed by a single letter and a number", "id": "3_3711"}, {"layer": 2, "feature": 7630, "explanation": "names or references to a specific individual marked with \"K9\"", "id": "2_7630"}, {"layer": 4, "feature": 22656, "explanation": "the letter \"K\" followed by a single digit", "id": "4_22656"}, {"layer": 1, "feature": 9093, "explanation": "names or initials starting with 'K'", "id": "1_9093"}, {"layer": 8, "feature": 4094, "explanation": "mentions or references to the letter \"K\" followed by numbers or names", "id": "8_4094"}], "links": [{"similarity": 0.997607409954071, "source": "6_23531", "target": "7_8901"}, {"similarity": 0.99540114402771, "source": "7_8901", "target": "8_4094"}, {"similarity": 0.9789763689041138, "source": "9_19353", "target": "10_11916"}, {"similarity": 0.5824828743934631, "source": "9_19353", "target": "10_17328"}, {"similarity": 0.3998221158981323, "source": "10_11916", "target": "11_5015"}, {"similarity": 0.9742299914360046, "source": "10_11916", "target": "11_14795"}, {"similarity": 0.5076289772987366, "source": "10_11916", "target": "11_15422"}, {"similarity": 0.9981914162635803, "source": "0_2368", "target": "1_9093"}, {"similarity": 0.2052568793296814, "source": "10_17328", "target": "11_5015"}, {"similarity": 0.30199679732322693, "source": "10_17328", "target": "11_14795"}, {"similarity": 0.9724742770195007, "source": "10_17328", "target": "11_15422"}, {"similarity": 0.9979153871536255, "source": "5_15445", "target": "6_23531"}, {"similarity": 0.9977362155914307, "source": "3_3711", "target": "4_22656"}, {"similarity": 0.9986141324043274, "source": "2_7630", "target": "3_3711"}, {"similarity": 0.997852087020874, "source": "4_22656", "target": "5_15445"}, {"similarity": 0.9959232211112976, "source": "1_9093", "target": "2_7630"}, {"similarity": 0.996803879737854, "source": "8_4094", "target": "9_19353"}]}