{"directed": true, "multigraph": false, "graph": {}, "nodes": [{"layer": 6, "feature": 12801, "explanation": "instances of the word \"windows\" combined with a number indicating the relevance or importance of the windows", "id": "6_12801"}, {"layer": 7, "feature": 17535, "explanation": "references to physical windows", "id": "7_17535"}, {"layer": 8, "feature": 5211, "explanation": "keywords related to different versions of Windows operating system", "id": "8_5211"}, {"layer": 7, "feature": 14484, "explanation": "mentions of different versions of the Windows operating system", "id": "7_14484"}, {"layer": 4, "feature": 23705, "explanation": "phrases mentioning actions related to windows", "id": "4_23705"}, {"layer": 9, "feature": 23042, "explanation": "windows mentioned in a physical context", "id": "9_23042"}, {"layer": 4, "feature": 2852, "explanation": "references to different versions of the Windows operating system", "id": "4_2852"}, {"layer": 3, "feature": 10538, "explanation": "instances of the word \"windows\"", "id": "3_10538"}, {"layer": 4, "feature": 11632, "explanation": "URLs and commands related to opening new windows or modifying browser properties", "id": "4_11632"}, {"layer": 6, "feature": 6454, "explanation": "references to different versions of the Windows operating system", "id": "6_6454"}, {"layer": 6, "feature": 9352, "explanation": "references to browser windows or interfaces", "id": "6_9352"}, {"layer": 8, "feature": 15442, "explanation": "descriptions of physical windows", "id": "8_15442"}, {"layer": 5, "feature": 5494, "explanation": "references to different versions of the Windows operating system", "id": "5_5494"}, {"layer": 2, "feature": 18315, "explanation": "phrases or contexts related to the concept of \"window.\"", "id": "2_18315"}, {"layer": 3, "feature": 15824, "explanation": "references to time windows", "id": "3_15824"}, {"layer": 5, "feature": 6339, "explanation": "links or commands related to opening new windows or popup windows", "id": "5_6339"}, {"layer": 11, "feature": 15602, "explanation": "references to windows and their characteristics", "id": "11_15602"}, {"layer": 10, "feature": 8827, "explanation": "references to windows in various contexts", "id": "10_8827"}, {"layer": 5, "feature": 3873, "explanation": "references to windows, especially when associated with various actions or descriptions like smashing, installing, or having certain characteristics like being small or tinted", "id": "5_3873"}, {"layer": 4, "feature": 46, "explanation": "instances of the word \"windows\"", "id": "4_46"}], "links": [{"similarity": 0.1031746044754982, "source": "6_12801", "target": "7_14484"}, {"similarity": 0.6005089282989502, "source": "6_12801", "target": "7_17535"}, {"similarity": 0.16839377582073212, "source": "7_17535", "target": "8_5211"}, {"similarity": 0.9873577952384949, "source": "7_17535", "target": "8_15442"}, {"similarity": 0.9455958604812622, "source": "7_14484", "target": "8_5211"}, {"similarity": 0.6638830900192261, "source": "4_23705", "target": "5_3873"}, {"similarity": 0.726210355758667, "source": "4_23705", "target": "5_6339"}, {"similarity": 0.9885786771774292, "source": "9_23042", "target": "10_8827"}, {"similarity": 0.8602941036224365, "source": "4_2852", "target": "5_5494"}, {"similarity": 0.9894459247589111, "source": "3_10538", "target": "4_46"}, {"similarity": 0.21367521584033966, "source": "3_10538", "target": "4_2852"}, {"similarity": 0.3221052587032318, "source": "3_10538", "target": "4_11632"}, {"similarity": 0.5752895474433899, "source": "3_10538", "target": "4_23705"}, {"similarity": 0.22546972334384918, "source": "4_11632", "target": "5_3873"}, {"similarity": 0.2450980395078659, "source": "4_11632", "target": "5_5494"}, {"similarity": 0.6911519169807434, "source": "4_11632", "target": "5_6339"}, {"similarity": 0.9894179701805115, "source": "6_6454", "target": "7_14484"}, {"similarity": 0.1005089059472084, "source": "6_6454", "target": "7_17535"}, {"similarity": 0.14814814925193787, "source": "6_9352", "target": "7_14484"}, {"similarity": 0.7493638396263123, "source": "6_9352", "target": "7_17535"}, {"similarity": 0.9936467409133911, "source": "8_15442", "target": "9_23042"}, {"similarity": 0.9741601943969727, "source": "5_5494", "target": "6_6454"}, {"similarity": 0.10887771844863892, "source": "5_5494", "target": "6_9352"}, {"similarity": 0.15082643926143646, "source": "5_5494", "target": "6_12801"}, {"similarity": 0.4173228442668915, "source": "2_18315", "target": "3_10538"}, {"similarity": 0.8989361524581909, "source": "2_18315", "target": "3_15824"}, {"similarity": 0.36939314007759094, "source": "3_15824", "target": "4_46"}, {"similarity": 0.8105263113975525, "source": "3_15824", "target": "4_11632"}, {"similarity": 0.8359073400497437, "source": "3_15824", "target": "4_23705"}, {"similarity": 0.13953489065170288, "source": "5_6339", "target": "6_6454"}, {"similarity": 0.9916247725486755, "source": "5_6339", "target": "6_9352"}, {"similarity": 0.60537189245224, "source": "5_6339", "target": "6_12801"}, {"similarity": 0.9712139964103699, "source": "10_8827", "target": "11_15602"}, {"similarity": 0.4757118821144104, "source": "5_3873", "target": "6_9352"}, {"similarity": 0.952479362487793, "source": "5_3873", "target": "6_12801"}, {"similarity": 0.6617953777313232, "source": "4_46", "target": "5_3873"}, {"similarity": 0.3063725531101227, "source": "4_46", "target": "5_5494"}, {"similarity": 0.27879798412323, "source": "4_46", "target": "5_6339"}]}