{"directed": true, "multigraph": false, "graph": {}, "nodes": [{"layer": 6, "feature": 23653, "explanation": "words related to information", "id": "6_23653"}, {"layer": 11, "feature": 9298, "explanation": "the word \"Inferno\"", "id": "11_9298"}, {"layer": 11, "feature": 1924, "explanation": "phrases related to the concept of influence or infiltration", "id": "11_1924"}, {"layer": 7, "feature": 10493, "explanation": "keywords related to a specific online news platform named \"Infowars.\"", "id": "7_10493"}, {"layer": 5, "feature": 15685, "explanation": "mentions of drug-related terms", "id": "5_15685"}, {"layer": 9, "feature": 21504, "explanation": "phrases related to conflict, law enforcement, and accountability", "id": "9_21504"}, {"layer": 8, "feature": 17313, "explanation": "phrases or words related to information, frequently emphasizing intensity or urgency, such as 'infusing', 'infidelity', or 'infanticide'", "id": "8_17313"}, {"layer": 3, "feature": 7246, "explanation": "specific keyword related to information technology and data security, specifically the term \"Infiltrates\"", "id": "3_7246"}, {"layer": 2, "feature": 23069, "explanation": "words related to influence or impact", "id": "2_23069"}, {"layer": 10, "feature": 8200, "explanation": "mentions of web links or internet references", "id": "10_8200"}, {"layer": 2, "feature": 12763, "explanation": "specific mentions of the term 'Inf' or 'Infractions'", "id": "2_12763"}, {"layer": 7, "feature": 1480, "explanation": "medical terms or phrases related to health conditions", "id": "7_1480"}, {"layer": 9, "feature": 23703, "explanation": "terms related to information or specific data", "id": "9_23703"}, {"layer": 3, "feature": 24202, "explanation": "word roots related to negative connotations", "id": "3_24202"}, {"layer": 5, "feature": 19104, "explanation": "mentions of a particular word with a common prefix 'Inf' followed by a varying number", "id": "5_19104"}, {"layer": 2, "feature": 13650, "explanation": "words related to information technology and digital media", "id": "2_13650"}, {"layer": 6, "feature": 6679, "explanation": "mentions of the term \"Inf\" followed by a number, such as \"Inf8\" or \"Inf9\"", "id": "6_6679"}, {"layer": 10, "feature": 17556, "explanation": "words related to the concept of \"infusion.\"", "id": "10_17556"}, {"layer": 4, "feature": 19032, "explanation": "specific mentions of the term \"Inf\" at various locations in the text", "id": "4_19032"}, {"layer": 5, "feature": 12193, "explanation": "words related to infidelity", "id": "5_12193"}, {"layer": 8, "feature": 23535, "explanation": "phrases related to the news media or reporting, specifically mentioning a platform called \"InfoWars.\"", "id": "8_23535"}, {"layer": 3, "feature": 14679, "explanation": "phrases related to the influence of drugs or alcohol", "id": "3_14679"}, {"layer": 4, "feature": 10245, "explanation": "words related to influence or impact", "id": "4_10245"}, {"layer": 4, "feature": 3951, "explanation": "words related to the concept of 'infidelity'", "id": "4_3951"}], "links": [{"similarity": 0.9740518927574158, "source": "6_23653", "target": "7_1480"}, {"similarity": 0.45309382677078247, "source": "6_23653", "target": "7_10493"}, {"similarity": 0.8507042527198792, "source": "7_10493", "target": "8_17313"}, {"similarity": 0.997183084487915, "source": "7_10493", "target": "8_23535"}, {"similarity": 0.9087837934494019, "source": "5_15685", "target": "6_6679"}, {"similarity": 0.6351351141929626, "source": "5_15685", "target": "6_23653"}, {"similarity": 1.0, "source": "9_21504", "target": "10_17556"}, {"similarity": 0.4826388955116272, "source": "8_17313", "target": "9_21504"}, {"similarity": 0.8541666865348816, "source": "8_17313", "target": "9_23703"}, {"similarity": 0.6964285969734192, "source": "3_7246", "target": "4_10245"}, {"similarity": 0.8928571343421936, "source": "3_7246", "target": "4_19032"}, {"similarity": 0.7222222089767456, "source": "2_23069", "target": "3_7246"}, {"similarity": 0.9740740656852722, "source": "2_23069", "target": "3_14679"}, {"similarity": 0.42941176891326904, "source": "10_8200", "target": "11_1924"}, {"similarity": 0.9764705896377563, "source": "10_8200", "target": "11_9298"}, {"similarity": 1.0, "source": "2_12763", "target": "3_7246"}, {"similarity": 0.46875, "source": "2_12763", "target": "3_14679"}, {"similarity": 0.9672414064407349, "source": "7_1480", "target": "8_17313"}, {"similarity": 0.5189655423164368, "source": "7_1480", "target": "8_23535"}, {"similarity": 0.6261510252952576, "source": "9_23703", "target": "10_8200"}, {"similarity": 0.7237569093704224, "source": "9_23703", "target": "10_17556"}, {"similarity": 1.0, "source": "3_24202", "target": "4_3951"}, {"similarity": 0.982758641242981, "source": "5_19104", "target": "6_6679"}, {"similarity": 0.3965517282485962, "source": "5_19104", "target": "6_23653"}, {"similarity": 1.0, "source": "2_13650", "target": "3_24202"}, {"similarity": 0.8478873372077942, "source": "6_6679", "target": "7_1480"}, {"similarity": 0.9887323975563049, "source": "6_6679", "target": "7_10493"}, {"similarity": 0.857442319393158, "source": "10_17556", "target": "11_1924"}, {"similarity": 0.4297693967819214, "source": "10_17556", "target": "11_9298"}, {"similarity": 0.692307710647583, "source": "4_19032", "target": "5_15685"}, {"similarity": 0.6346153616905212, "source": "4_19032", "target": "5_19104"}, {"similarity": 1.0, "source": "5_12193", "target": "6_23653"}, {"similarity": 0.9803370833396912, "source": "8_23535", "target": "9_23703"}, {"similarity": 0.9241379499435425, "source": "3_14679", "target": "4_10245"}, {"similarity": 0.6034482717514038, "source": "3_14679", "target": "4_19032"}, {"similarity": 0.9566666483879089, "source": "4_10245", "target": "5_15685"}, {"similarity": 0.2666666805744171, "source": "4_10245", "target": "5_19104"}, {"similarity": 0.9551724195480347, "source": "4_3951", "target": "5_12193"}]}