{"directed": true, "multigraph": false, "graph": {}, "nodes": [{"layer": 0, "feature": 74, "explanation": "phrases related to investigating, exploring, or delving into various subjects or situations", "community": 148, "id": "0_74"}, {"layer": 0, "feature": 2280, "explanation": "words related to physical tearing or damage", "community": 2354, "id": "0_2280"}, {"layer": 0, "feature": 3187, "explanation": "phrases related to news and events coverage", "community": 1, "id": "0_3187"}, {"layer": 0, "feature": 3444, "explanation": "verbs or phrases related to tearing or causing tears", "community": 3515, "id": "0_3444"}, {"layer": 0, "feature": 5263, "explanation": "words related to medical terms or anatomy", "community": 5333, "id": "0_5263"}, {"layer": 0, "feature": 9440, "explanation": "dates and events", "community": 1, "id": "0_9440"}, {"layer": 0, "feature": 9895, "explanation": "words related to medical conditions and terms like \"prevalence rate\" and \"idiopathic\"", "community": 1, "id": "0_9895"}, {"layer": 0, "feature": 12047, "explanation": "names of specific individuals", "community": 1, "id": "0_12047"}, {"layer": 0, "feature": 16898, "explanation": "phrases related to physical impact or force, particularly actions involving hitting or striking", "community": 16952, "id": "0_16898"}, {"layer": 0, "feature": 19133, "explanation": "phrases related to military or conflict operations", "community": 19185, "id": "0_19133"}, {"layer": 0, "feature": 20949, "explanation": "mentions of physical and emotional pain", "community": 21000, "id": "0_20949"}, {"layer": 0, "feature": 23998, "explanation": "terms related to the word \"mantle\"", "community": 24046, "id": "0_23998"}, {"layer": 1, "feature": 113, "explanation": "medical terms related to conditions involving the heart and blood vessels", "community": 24736, "id": "1_113"}, {"layer": 1, "feature": 4329, "explanation": "words related to justification or acknowledgment", "community": 28950, "id": "1_4329"}, {"layer": 1, "feature": 6831, "explanation": "mentions of digital communication or coding-related text", "community": 1, "id": "1_6831"}, {"layer": 1, "feature": 11003, "explanation": "terms related to plastic materials such as PVC, polystyrene, copolymers, film, and chemical substances", "community": 35614, "id": "1_11003"}, {"layer": 1, "feature": 11587, "explanation": "references to specific names or places", "community": 1, "id": "1_11587"}, {"layer": 1, "feature": 14479, "explanation": "mentions of personal interactions or connections", "community": 1, "id": "1_14479"}, {"layer": 1, "feature": 15656, "explanation": "actions related to forceful tearing or destruction", "community": 40260, "id": "1_15656"}, {"layer": 1, "feature": 17104, "explanation": "phrases related to proportion and quantity", "community": 41708, "id": "1_17104"}, {"layer": 1, "feature": 17691, "explanation": "terms related to technical details and weaponry", "community": 42295, "id": "1_17691"}, {"layer": 1, "feature": 19865, "explanation": "universities and colleges names", "community": 1, "id": "1_19865"}, {"layer": 1, "feature": 21300, "explanation": "mentions of bodily fluids and medical substances", "community": 45900, "id": "1_21300"}, {"layer": 1, "feature": 21669, "explanation": "actions related to physical movements and activities", "community": 46269, "id": "1_21669"}, {"layer": 1, "feature": 21930, "explanation": "references to tear gas and similar riot control weapons", "community": 46530, "id": "1_21930"}, {"layer": 1, "feature": 23571, "explanation": "proper nouns related to people and places", "community": 48169, "id": "1_23571"}, {"layer": 2, "feature": 891, "explanation": "items related to different categories such as leisure activities, industries, and medical conditions", "community": 50058, "id": "2_891"}, {"layer": 2, "feature": 946, "explanation": "mentions of negatively viewed actions or states", "community": 50113, "id": "2_946"}, {"layer": 2, "feature": 1351, "explanation": "terms related to education and academia", "community": 50518, "id": "2_1351"}, {"layer": 2, "feature": 2045, "explanation": "words related to tear gas", "community": 51211, "id": "2_2045"}, {"layer": 2, "feature": 2673, "explanation": "verbs related to forceful actions or destruction", "community": 51839, "id": "2_2673"}, {"layer": 2, "feature": 4761, "explanation": "phrases related to repetition and continuous actions", "community": 53924, "id": "2_4761"}, {"layer": 2, "feature": 5517, "explanation": "descriptions of physical locations and actions related to being in or around a building", "community": 54680, "id": "2_5517"}, {"layer": 2, "feature": 5908, "explanation": "terms related to legal proceedings and political journalism", "community": 55070, "id": "2_5908"}, {"layer": 2, "feature": 7530, "explanation": "verbs related to multiplication or making something double", "community": 56689, "id": "2_7530"}, {"layer": 2, "feature": 8862, "explanation": "descriptions of different materials and finishes in relation to items or products", "community": 58021, "id": "2_8862"}, {"layer": 2, "feature": 9432, "explanation": "physical actions or movements", "community": 58591, "id": "2_9432"}, {"layer": 2, "feature": 12727, "explanation": "terms related to supply chain and logistics", "community": 1, "id": "2_12727"}, {"layer": 2, "feature": 12894, "explanation": "words related to ethics, spending, medical cases, and legal actions", "community": 22, "id": "2_12894"}, {"layer": 2, "feature": 15843, "explanation": "references to the TV show \"The Walking Dead\"", "community": 64993, "id": "2_15843"}, {"layer": 2, "feature": 17302, "explanation": "mathematical terms and equations", "community": 66449, "id": "2_17302"}, {"layer": 2, "feature": 20343, "explanation": "words related to tools and construction equipment", "community": 69487, "id": "2_20343"}, {"layer": 2, "feature": 21325, "explanation": "mentions of physical injuries or damage", "community": 70469, "id": "2_21325"}, {"layer": 2, "feature": 21401, "explanation": "country names", "community": 1, "id": "2_21401"}, {"layer": 2, "feature": 22748, "explanation": "words related to negative or critical commentary", "community": 71891, "id": "2_22748"}, {"layer": 2, "feature": 23585, "explanation": "phrases related to medical conditions and body parts in the context of blood circulation and diseases", "community": 72726, "id": "2_23585"}, {"layer": 2, "feature": 23706, "explanation": "keywords related to computer code and programming languages", "community": 72847, "id": "2_23706"}, {"layer": 3, "feature": 2948, "explanation": "words related to physical activities or movements", "community": 76662, "id": "3_2948"}, {"layer": 3, "feature": 4512, "explanation": "words or phrases indicating a change or significant impact", "community": 78226, "id": "3_4512"}, {"layer": 3, "feature": 7516, "explanation": "numbers", "community": 81228, "id": "3_7516"}, {"layer": 3, "feature": 8111, "explanation": "anatomy and body parts related to the lower abdomen and thighs", "community": 81822, "id": "3_8111"}, {"layer": 3, "feature": 9288, "explanation": "words related to negative social or political topics", "community": 82999, "id": "3_9288"}, {"layer": 3, "feature": 9458, "explanation": "specific actions or operations described with strong verbs", "community": 83169, "id": "3_9458"}, {"layer": 3, "feature": 9465, "explanation": "words related to forceful tearing or destruction", "community": 83176, "id": "3_9465"}, {"layer": 3, "feature": 10195, "explanation": "words related to physical symptoms and medical conditions", "community": 83906, "id": "3_10195"}, {"layer": 3, "feature": 10420, "explanation": "action verbs related to physical movement or interaction", "community": 84131, "id": "3_10420"}, {"layer": 3, "feature": 15617, "explanation": "patterns or instructions related to sewing", "community": 89326, "id": "3_15617"}, {"layer": 3, "feature": 17242, "explanation": "information related to recent events or news articles", "community": 1, "id": "3_17242"}, {"layer": 3, "feature": 18082, "explanation": "verbs related to planning, organizing, and scheduling events or activities", "community": 91790, "id": "3_18082"}, {"layer": 3, "feature": 18814, "explanation": "words related to physical actions involving the body such as rubbing, biting, coughing, barking, sweating, kissing, slicing, clicking, splitting, cutting, harvesting, sucking, locking, smashing, stirring", "community": 92521, "id": "3_18814"}, {"layer": 3, "feature": 18863, "explanation": "verbs related to actions or events", "community": 92569, "id": "3_18863"}, {"layer": 3, "feature": 19858, "explanation": "mentions of legal and regulatory language related to corporate entities", "community": 93563, "id": "3_19858"}, {"layer": 3, "feature": 21861, "explanation": "technical terms related to technology and science", "community": 1, "id": "3_21861"}, {"layer": 3, "feature": 23064, "explanation": "terms related to societal issues such as diversity, compassion, guilt, and specific societal groups like Republicans or white men", "community": 96765, "id": "3_23064"}, {"layer": 3, "feature": 23093, "explanation": "words related to government actions and legislative processes", "community": 22, "id": "3_23093"}, {"layer": 3, "feature": 24281, "explanation": "words related to tear gas", "community": 97981, "id": "3_24281"}, {"layer": 3, "feature": 24542, "explanation": "measurements expressed in inches", "community": 98241, "id": "3_24542"}, {"layer": 4, "feature": 15, "explanation": "words related to violent actions or events", "community": 98290, "id": "4_15"}, {"layer": 4, "feature": 837, "explanation": " verbs describing actions or activities", "community": 99111, "id": "4_837"}, {"layer": 4, "feature": 1750, "explanation": "symptoms and medical conditions related to inflammation and injury", "community": 100021, "id": "4_1750"}, {"layer": 4, "feature": 2287, "explanation": "verbs related to actions or changes that have significant impact or consequences", "community": 100558, "id": "4_2287"}, {"layer": 4, "feature": 2876, "explanation": "different types of grains and drugs", "community": 101147, "id": "4_2876"}, {"layer": 4, "feature": 6393, "explanation": "verbs or actions related to manipulating or altering something", "community": 104660, "id": "4_6393"}, {"layer": 4, "feature": 6452, "explanation": "verbs indicating attempts or actions", "community": 104719, "id": "4_6452"}, {"layer": 4, "feature": 6462, "explanation": "technical terms and keywords related to different subjects, such as technology and legal matters", "community": 104729, "id": "4_6462"}, {"layer": 4, "feature": 7410, "explanation": "actions involving physical force or effort, such as pushing, pulling, grabbing, and tugging", "community": 105676, "id": "4_7410"}, {"layer": 4, "feature": 7715, "explanation": "terms related to technology and business operations", "community": 105980, "id": "4_7715"}, {"layer": 4, "feature": 7936, "explanation": "phrases related to forcefully opening or destroying something", "community": 106201, "id": "4_7936"}, {"layer": 4, "feature": 10283, "explanation": "words related to technical operations and configurations", "community": 108547, "id": "4_10283"}, {"layer": 4, "feature": 11189, "explanation": "terms related to physical interactions and processes involving movement or change", "community": 109451, "id": "4_11189"}, {"layer": 4, "feature": 12274, "explanation": "words related to change or adaptation", "community": 110536, "id": "4_12274"}, {"layer": 4, "feature": 13869, "explanation": "words related to structural or formal subjects like organizations, institutions, or procedures", "community": 112130, "id": "4_13869"}, {"layer": 4, "feature": 15235, "explanation": "concepts related to law, legal proceedings, and regulations", "community": 22, "id": "4_15235"}, {"layer": 4, "feature": 15552, "explanation": "phrases related to unusual or disruptive actions", "community": 113811, "id": "4_15552"}, {"layer": 4, "feature": 20671, "explanation": "technical and construction-related terms", "community": 118925, "id": "4_20671"}, {"layer": 4, "feature": 20929, "explanation": "processes involving assembling or connecting objects together physically", "community": 119183, "id": "4_20929"}, {"layer": 4, "feature": 21515, "explanation": "terms related to activism and social issues", "community": 119768, "id": "4_21515"}, {"layer": 4, "feature": 21881, "explanation": "words related to persistence or consistency", "community": 120134, "id": "4_21881"}, {"layer": 4, "feature": 21937, "explanation": "actions related to crafting and creating objects", "community": 120190, "id": "4_21937"}, {"layer": 4, "feature": 23042, "explanation": "terms related to different types of trading activities", "community": 121292, "id": "4_23042"}, {"layer": 4, "feature": 23058, "explanation": "instances of tear gas being used", "community": 121308, "id": "4_23058"}, {"layer": 4, "feature": 23241, "explanation": "terms related to physical exertion or achievement", "community": 46, "id": "4_23241"}, {"layer": 4, "feature": 23539, "explanation": "words related to natural elements or objects", "community": 121787, "id": "4_23539"}, {"layer": 4, "feature": 24324, "explanation": "verbs related to actions and tasks", "community": 122572, "id": "4_24324"}, {"layer": 5, "feature": 647, "explanation": "action verbs related to changing, fixing, or transforming things", "community": 123471, "id": "5_647"}, {"layer": 5, "feature": 911, "explanation": "verbs related to physical actions or processes", "community": 123735, "id": "5_911"}, {"layer": 5, "feature": 1602, "explanation": "words related to processed data or information", "community": 124426, "id": "5_1602"}, {"layer": 5, "feature": 2052, "explanation": "phrases related to chaos or disruptive events", "community": 124876, "id": "5_2052"}, {"layer": 5, "feature": 2068, "explanation": "action verbs that denote strong or impactful actions", "community": 124892, "id": "5_2068"}, {"layer": 5, "feature": 2361, "explanation": "terms related to processing or organizing information for efficiency", "community": 125185, "id": "5_2361"}, {"layer": 5, "feature": 2600, "explanation": "phrases and words related to physical impacts and collisions", "community": 125424, "id": "5_2600"}, {"layer": 5, "feature": 3173, "explanation": "common phrases related to academic, technical, and scientific topics, such as data analysis, classification, CPU specifications, and more", "community": 125997, "id": "5_3173"}, {"layer": 5, "feature": 3935, "explanation": "technical terms related to computation", "community": 126758, "id": "5_3935"}, {"layer": 5, "feature": 7418, "explanation": "phrases related to educational activities and instructions", "community": 130237, "id": "5_7418"}, {"layer": 5, "feature": 8488, "explanation": "words related to actions or processes, particularly involving physical activities or operations", "community": 131304, "id": "5_8488"}, {"layer": 5, "feature": 10484, "explanation": "dates mentioned in legal or official declarations", "community": 10, "id": "5_10484"}, {"layer": 5, "feature": 10782, "explanation": "technical terms and company names related to technology and finance", "community": 133594, "id": "5_10782"}, {"layer": 5, "feature": 10986, "explanation": "phrases indicating contrast or emphasizing change", "community": 133797, "id": "5_10986"}, {"layer": 5, "feature": 12464, "explanation": "physical descriptions and medical conditions", "community": 135272, "id": "5_12464"}, {"layer": 5, "feature": 13834, "explanation": "words related to tear gas and tearful situations", "community": 136642, "id": "5_13834"}, {"layer": 5, "feature": 15609, "explanation": "verbs related to decision-making or actions", "community": 138417, "id": "5_15609"}, {"layer": 5, "feature": 18989, "explanation": "details related to actions and events", "community": 141796, "id": "5_18989"}, {"layer": 5, "feature": 19360, "explanation": " Phrases related to quantity or comparison", "community": 142167, "id": "5_19360"}, {"layer": 5, "feature": 19629, "explanation": "words related to magnetic fields and forces", "community": 142436, "id": "5_19629"}, {"layer": 5, "feature": 19760, "explanation": "terms related to economic policies, financial activities, and regulations", "community": 142567, "id": "5_19760"}, {"layer": 5, "feature": 20882, "explanation": "words related to programming and software development processes, such as \"compiling,\" \"exporting,\" \"cloning,\" and \"installing.\"", "community": 143688, "id": "5_20882"}, {"layer": 5, "feature": 22097, "explanation": "words related to criticisms and evaluations", "community": 144903, "id": "5_22097"}, {"layer": 5, "feature": 22263, "explanation": "mentions of physical injuries or damage", "community": 145069, "id": "5_22263"}, {"layer": 5, "feature": 23502, "explanation": "verbs related to forceful and destructive actions", "community": 146307, "id": "5_23502"}, {"layer": 5, "feature": 23542, "explanation": "phrases related to adjustable objects or equipment", "community": 146347, "id": "5_23542"}, {"layer": 5, "feature": 24134, "explanation": "phrases related to forceful or aggressive actions", "community": 146939, "id": "5_24134"}, {"layer": 6, "feature": 424, "explanation": "actions or procedures that involve physical activities or manipulations", "community": 147804, "id": "6_424"}, {"layer": 6, "feature": 1648, "explanation": "phrases related to physical activities and locations", "community": 149028, "id": "6_1648"}, {"layer": 6, "feature": 1706, "explanation": "keywords related to political events and actions", "community": 149086, "id": "6_1706"}, {"layer": 6, "feature": 2165, "explanation": "technology-related terms and concepts, with a focus on hardware and military", "community": 149545, "id": "6_2165"}, {"layer": 6, "feature": 2858, "explanation": "words related to physical injuries, specifically tearing", "community": 150238, "id": "6_2858"}, {"layer": 6, "feature": 2938, "explanation": "proper nouns related to various fields and individuals", "community": 150318, "id": "6_2938"}, {"layer": 6, "feature": 3457, "explanation": "words related to automotive parts or maintenance", "community": 150836, "id": "6_3457"}, {"layer": 6, "feature": 3580, "explanation": "physical symptoms and conditions related to swelling, itching, irritation, and inflammation", "community": 150959, "id": "6_3580"}, {"layer": 6, "feature": 3656, "explanation": "keywords related to physical and chemical processes, such as reactions, emissions, absorptions, and interactions", "community": 151035, "id": "6_3656"}, {"layer": 6, "feature": 5893, "explanation": "companies, products, or technical details", "community": 153270, "id": "6_5893"}, {"layer": 6, "feature": 6734, "explanation": "phrases related to contrasting viewpoints or different sides of an argument", "community": 154111, "id": "6_6734"}, {"layer": 6, "feature": 6761, "explanation": "phrases related to mechanical attributes and functions", "community": 154138, "id": "6_6761"}, {"layer": 6, "feature": 6978, "explanation": "terms related to negative events or situations, such as bullying, failure, and spillages", "community": 154355, "id": "6_6978"}, {"layer": 6, "feature": 7422, "explanation": "adjectives or adverbs indicating extremity or intensity", "community": 154799, "id": "6_7422"}, {"layer": 6, "feature": 8975, "explanation": "verbs related to forceful actions or destruction", "community": 156352, "id": "6_8975"}, {"layer": 6, "feature": 9183, "explanation": "technical actions related to software development and computer operations", "community": 156560, "id": "6_9183"}, {"layer": 6, "feature": 9469, "explanation": "verbs related to physical actions or changes", "community": 156846, "id": "6_9469"}, {"layer": 6, "feature": 9505, "explanation": "actions or instructions involving covering, wrapping, or overlaying objects", "community": 156882, "id": "6_9505"}, {"layer": 6, "feature": 10782, "explanation": "The neuron is specifically searching for words related to tear gas", "community": 158158, "id": "6_10782"}, {"layer": 6, "feature": 11026, "explanation": "instructions or warnings related to potential harm or danger", "community": 158402, "id": "6_11026"}, {"layer": 6, "feature": 11514, "explanation": "statistical or numerical information", "community": 158890, "id": "6_11514"}, {"layer": 6, "feature": 12763, "explanation": "words related to negotiations, plans, concerns, and arrangements", "community": 160137, "id": "6_12763"}, {"layer": 6, "feature": 13937, "explanation": "verbs related to actions involving changes or effects on something", "community": 161310, "id": "6_13937"}, {"layer": 6, "feature": 14853, "explanation": "sequences related to legal and public documents, such as terms indicating legal issues, characters, and specific details of legal cases", "community": 10, "id": "6_14853"}, {"layer": 6, "feature": 15143, "explanation": "adjectives or verbs describing intense or dramatic actions", "community": 162513, "id": "6_15143"}, {"layer": 6, "feature": 15334, "explanation": "terms related to educational settings or facilities", "community": 162704, "id": "6_15334"}, {"layer": 6, "feature": 15553, "explanation": "terms related to magnetic fields", "community": 162923, "id": "6_15553"}, {"layer": 6, "feature": 15793, "explanation": "terms related to legal language and clauses", "community": 163163, "id": "6_15793"}, {"layer": 6, "feature": 16018, "explanation": "financial and economic terms", "community": 163388, "id": "6_16018"}, {"layer": 6, "feature": 18234, "explanation": "action words related to technology and settings", "community": 165604, "id": "6_18234"}, {"layer": 6, "feature": 18599, "explanation": "legal and policy-related terms and concepts", "community": 165969, "id": "6_18599"}, {"layer": 6, "feature": 19730, "explanation": "words related to negative or criminal activities, such as trouble, jail, arrested, or bankrupt", "community": 167099, "id": "6_19730"}, {"layer": 6, "feature": 21873, "explanation": "verbs related to physical actions involving pulling or tugging", "community": 169242, "id": "6_21873"}, {"layer": 6, "feature": 22070, "explanation": "words related to tools and equipment", "community": 169439, "id": "6_22070"}, {"layer": 6, "feature": 22464, "explanation": "proper nouns or names within a text", "community": 169833, "id": "6_22464"}, {"layer": 6, "feature": 22552, "explanation": "code-related terms and snippets", "community": 169921, "id": "6_22552"}, {"layer": 6, "feature": 23088, "explanation": "accomplishments or actions done by individuals", "community": 170457, "id": "6_23088"}, {"layer": 6, "feature": 23715, "explanation": "words related to legal and bureaucratic processes", "community": 171084, "id": "6_23715"}, {"layer": 6, "feature": 23760, "explanation": "words related to names", "community": 171129, "id": "6_23760"}, {"layer": 7, "feature": 34, "explanation": "action verbs expressing accomplishment or achievement", "community": 171978, "id": "7_34"}, {"layer": 7, "feature": 36, "explanation": "words related to specific tasks or actions like software operations", "community": 171980, "id": "7_36"}, {"layer": 7, "feature": 1029, "explanation": "medical conditions or symptoms related to the skin, muscles, or internal organs", "community": 172972, "id": "7_1029"}, {"layer": 7, "feature": 1426, "explanation": "terms related to specific entities or topics within various contexts, such as road safety, Iron Man, European countries, etc", "community": 173369, "id": "7_1426"}, {"layer": 7, "feature": 2547, "explanation": "references to tear gas and related activities", "community": 174490, "id": "7_2547"}, {"layer": 7, "feature": 2589, "explanation": "passive or negative terms related to consequences or actions", "community": 174532, "id": "7_2589"}, {"layer": 7, "feature": 3433, "explanation": "technical terms related to mechanical equipment and systems", "community": 175374, "id": "7_3433"}, {"layer": 7, "feature": 4576, "explanation": "legal terms and phrases", "community": 176515, "id": "7_4576"}, {"layer": 7, "feature": 5068, "explanation": "terms related to social issues, such as race, ethnicity, discrimination, and health disparities", "community": 177007, "id": "7_5068"}, {"layer": 7, "feature": 5138, "explanation": "references to physical injuries, specifically focusing on tears or damage", "community": 177077, "id": "7_5138"}, {"layer": 7, "feature": 7383, "explanation": "verbs expressing actions or activities", "community": 179321, "id": "7_7383"}, {"layer": 7, "feature": 8476, "explanation": "phrases related to management or leadership roles", "community": 180414, "id": "7_8476"}, {"layer": 7, "feature": 8717, "explanation": "names of people and political entities", "community": 180655, "id": "7_8717"}, {"layer": 7, "feature": 8725, "explanation": "negative outcomes or consequences", "community": 180663, "id": "7_8725"}, {"layer": 7, "feature": 9501, "explanation": "text related to construction and design, including keywords like 'safety', 'sturdy', and 'solution'", "community": 181439, "id": "7_9501"}, {"layer": 7, "feature": 9537, "explanation": "instances related to ripping or tearing actions", "community": 181475, "id": "7_9537"}, {"layer": 7, "feature": 12215, "explanation": "legal and bureaucratic terms, procedures, and actions", "community": 184151, "id": "7_12215"}, {"layer": 7, "feature": 12776, "explanation": "safety instructions for preventing injuries in various scenarios", "community": 184711, "id": "7_12776"}, {"layer": 7, "feature": 13626, "explanation": "technical terms related to systems and deviations from norms", "community": 185560, "id": "7_13626"}, {"layer": 7, "feature": 14759, "explanation": "information related to projects, participation, and choices", "community": 186690, "id": "7_14759"}, {"layer": 7, "feature": 14921, "explanation": "commands or actions related to file manipulation and programming", "community": 186852, "id": "7_14921"}, {"layer": 7, "feature": 15127, "explanation": "verbs associated with physical actions or activities", "community": 187058, "id": "7_15127"}, {"layer": 7, "feature": 15954, "explanation": "words related to physical actions or activities", "community": 187885, "id": "7_15954"}, {"layer": 7, "feature": 16037, "explanation": "references to historical events and societal structures", "community": 187968, "id": "7_16037"}, {"layer": 7, "feature": 16265, "explanation": "scientific, technical terms or specialized vocabulary", "community": 188196, "id": "7_16265"}, {"layer": 7, "feature": 17514, "explanation": "names of specific individuals and entities", "community": 189445, "id": "7_17514"}, {"layer": 7, "feature": 17662, "explanation": "keywords related to specific actions or instructions", "community": 189593, "id": "7_17662"}, {"layer": 7, "feature": 18216, "explanation": "technical terms and keywords related to computer programming and data management", "community": 190147, "id": "7_18216"}, {"layer": 7, "feature": 18518, "explanation": "words related to companies or business activities", "community": 190449, "id": "7_18518"}, {"layer": 7, "feature": 19643, "explanation": "phrases and terms related to astronomy and physics", "community": 191572, "id": "7_19643"}, {"layer": 7, "feature": 19879, "explanation": "specific details or components within a sentence", "community": 191808, "id": "7_19879"}, {"layer": 7, "feature": 20015, "explanation": "phrases related to legal terms and conditions", "community": 191944, "id": "7_20015"}, {"layer": 7, "feature": 20369, "explanation": "words related to physical changes or alterations", "community": 192296, "id": "7_20369"}, {"layer": 7, "feature": 20518, "explanation": "violent actions or descriptions, including tearing, ripping, and chopping", "community": 192445, "id": "7_20518"}, {"layer": 7, "feature": 20838, "explanation": "features related to image editing and visual effects such as shadows, reflections, highlights, and transformations", "community": 192765, "id": "7_20838"}, {"layer": 7, "feature": 20897, "explanation": "terms related to legal documents and official declarations", "community": 192824, "id": "7_20897"}, {"layer": 7, "feature": 21589, "explanation": "words related to technical tasks and operations", "community": 193515, "id": "7_21589"}, {"layer": 7, "feature": 21928, "explanation": "details related to instructions or steps", "community": 193854, "id": "7_21928"}, {"layer": 7, "feature": 23866, "explanation": "keywords related to time and events", "community": 195791, "id": "7_23866"}, {"layer": 8, "feature": 856, "explanation": "mentions of famous individuals and agreements", "community": 197357, "id": "8_856"}, {"layer": 8, "feature": 2019, "explanation": "phrases related to conflict and resolution", "community": 198519, "id": "8_2019"}, {"layer": 8, "feature": 2280, "explanation": "references to tear gas", "community": 198779, "id": "8_2280"}, {"layer": 8, "feature": 3097, "explanation": "words related to actions or events that involve a significant change or impact", "community": 199596, "id": "8_3097"}, {"layer": 8, "feature": 3330, "explanation": "common mistakes made by people in various contexts", "community": 199829, "id": "8_3330"}, {"layer": 8, "feature": 3341, "explanation": "phrases related to physical actions or processes", "community": 199840, "id": "8_3341"}, {"layer": 8, "feature": 3413, "explanation": "proper nouns related to various people, places, and organizations", "community": 199912, "id": "8_3413"}, {"layer": 8, "feature": 4444, "explanation": "phrases related to comparisons or contrasts", "community": 200942, "id": "8_4444"}, {"layer": 8, "feature": 4852, "explanation": "terms related to technical processes, specifically actions ending with 'ing' such as caching, mining, processing, lighting, cataloguing, and troubleshooting", "community": 201348, "id": "8_4852"}, {"layer": 8, "feature": 4900, "explanation": "technical terms and jargon related to technology and industry partnerships", "community": 201396, "id": "8_4900"}, {"layer": 8, "feature": 6401, "explanation": "ways to prevent physical objects from breaking or slipping", "community": 202897, "id": "8_6401"}, {"layer": 8, "feature": 6614, "explanation": "negative or harmful actions and characteristics", "community": 203110, "id": "8_6614"}, {"layer": 8, "feature": 6818, "explanation": "phrases related to sports and competition", "community": 203313, "id": "8_6818"}, {"layer": 8, "feature": 6844, "explanation": "terms related to technical issues such as memory leaks, corrosion, distraction, mold, pollution, and dehydration", "community": 203339, "id": "8_6844"}, {"layer": 8, "feature": 7902, "explanation": "adjectives related to value or magnitude", "community": 204396, "id": "8_7902"}, {"layer": 8, "feature": 7915, "explanation": "actions or tasks that are attempted but not successful", "community": 204409, "id": "8_7915"}, {"layer": 8, "feature": 7986, "explanation": "verbs ending in '-ing' with a focus on actions or processes", "community": 204479, "id": "8_7986"}, {"layer": 8, "feature": 8202, "explanation": "terms related to legal, financial, and political matters", "community": 204695, "id": "8_8202"}, {"layer": 8, "feature": 8937, "explanation": "keywords related to legal and financial matters", "community": 205430, "id": "8_8937"}, {"layer": 8, "feature": 9433, "explanation": "terms related to computer programming and technical concepts", "community": 205923, "id": "8_9433"}, {"layer": 8, "feature": 10200, "explanation": "phrases related to violence and conflict", "community": 206688, "id": "8_10200"}, {"layer": 8, "feature": 10698, "explanation": "activities related to outdoor sports or hobbies", "community": 207186, "id": "8_10698"}, {"layer": 8, "feature": 10836, "explanation": "phrases related to legal and international incidents", "community": 207324, "id": "8_10836"}, {"layer": 8, "feature": 10939, "explanation": "descriptive phrases related to objects being placed or secured in a specific location", "community": 207427, "id": "8_10939"}, {"layer": 8, "feature": 11216, "explanation": " words related to military actions and strategies", "community": 207703, "id": "8_11216"}, {"layer": 8, "feature": 11859, "explanation": "phrases related to copyright, analysis, health care, and recommendations", "community": 208346, "id": "8_11859"}, {"layer": 8, "feature": 14083, "explanation": "mention of work-related activities or tasks", "community": 210569, "id": "8_14083"}, {"layer": 8, "feature": 14866, "explanation": "adjectives or adverbs that express a strong level of certainty or intensity", "community": 211351, "id": "8_14866"}, {"layer": 8, "feature": 15735, "explanation": "information related to legal matters and criminal activities", "community": 212220, "id": "8_15735"}, {"layer": 8, "feature": 17717, "explanation": "quantitative limits or thresholds", "community": 214200, "id": "8_17717"}, {"layer": 8, "feature": 18606, "explanation": "phrases related to asserting opinions or beliefs", "community": 215088, "id": "8_18606"}, {"layer": 8, "feature": 18750, "explanation": "terms related to socio-political issues", "community": 215232, "id": "8_18750"}, {"layer": 8, "feature": 18782, "explanation": "technical terms related to processes or actions", "community": 215264, "id": "8_18782"}, {"layer": 8, "feature": 18995, "explanation": "medical conditions or physical symptoms", "community": 215477, "id": "8_18995"}, {"layer": 8, "feature": 19787, "explanation": "references to specific locations and natural phenomena, particularly related to environmental impact or physical events", "community": 216267, "id": "8_19787"}, {"layer": 8, "feature": 21505, "explanation": "information related to the preparation and usage of materials in various contexts, such as cooking, building, and crafting", "community": 217984, "id": "8_21505"}, {"layer": 8, "feature": 21508, "explanation": "content related to technological software and its features", "community": 217987, "id": "8_21508"}, {"layer": 8, "feature": 21537, "explanation": "technical terms and numerical values, potentially related to scientific or factual information", "community": 218016, "id": "8_21537"}, {"layer": 8, "feature": 21641, "explanation": "phrases related to forceful separation or destruction", "community": 218120, "id": "8_21641"}, {"layer": 8, "feature": 22394, "explanation": "topics related to race and ethnicity", "community": 218873, "id": "8_22394"}, {"layer": 8, "feature": 22430, "explanation": "usernames or names in a specific format", "community": 218909, "id": "8_22430"}, {"layer": 8, "feature": 22495, "explanation": "phrases indicating a call to action or decision-making", "community": 218974, "id": "8_22495"}, {"layer": 8, "feature": 22997, "explanation": "phrases related to legal and social regulations", "community": 219473, "id": "8_22997"}, {"layer": 8, "feature": 23424, "explanation": "instances of donations or charitable actions", "community": 219900, "id": "8_23424"}, {"layer": 8, "feature": 24344, "explanation": "legal terms and regulations in a document", "community": 220819, "id": "8_24344"}, {"layer": 9, "feature": 652, "explanation": "phrases related to teaching, training, or mentoring", "community": 221703, "id": "9_652"}, {"layer": 9, "feature": 781, "explanation": "terms related to specific actions or events in a professional or organizational context, such as freezing hiring, staffing, finances, or bonuses", "community": 221832, "id": "9_781"}, {"layer": 9, "feature": 941, "explanation": "words related to procedures, lists, and specific names", "community": 221992, "id": "9_941"}, {"layer": 9, "feature": 1018, "explanation": "activities or hobbies related to different outdoor and physical pursuits", "community": 222069, "id": "9_1018"}, {"layer": 9, "feature": 2060, "explanation": "descriptions of physical objects", "community": 223111, "id": "9_2060"}, {"layer": 9, "feature": 2276, "explanation": "verbs related to physical actions or movements", "community": 223327, "id": "9_2276"}, {"layer": 9, "feature": 3365, "explanation": "verbs related to action and change", "community": 224416, "id": "9_3365"}, {"layer": 9, "feature": 3711, "explanation": "medical conditions and treatments, particularly related to tumors and surgeries", "community": 224762, "id": "9_3711"}, {"layer": 9, "feature": 4356, "explanation": "phrases related to actions, decisions, and contributions", "community": 225406, "id": "9_4356"}, {"layer": 9, "feature": 6274, "explanation": "references to tear-inducing situations or objects", "community": 227322, "id": "9_6274"}, {"layer": 9, "feature": 7645, "explanation": "interesting mix of proper nouns and numerical values", "community": 228693, "id": "9_7645"}, {"layer": 9, "feature": 7647, "explanation": "names of specific locations or organizations", "community": 228695, "id": "9_7647"}, {"layer": 9, "feature": 8377, "explanation": "mentions of notable names, events, or entities", "community": 229421, "id": "9_8377"}, {"layer": 9, "feature": 8567, "explanation": "proper nouns and specific entities in text", "community": 229611, "id": "9_8567"}, {"layer": 9, "feature": 8829, "explanation": "adjectives related to a high level of significance or intensity", "community": 229873, "id": "9_8829"}, {"layer": 9, "feature": 9432, "explanation": "actions related to assembling or connecting objects", "community": 230472, "id": "9_9432"}, {"layer": 9, "feature": 9678, "explanation": "mentions of actions or scenarios related to competition, leveling, or development", "community": 230718, "id": "9_9678"}, {"layer": 9, "feature": 9850, "explanation": "references to political figures and actions", "community": 230890, "id": "9_9850"}, {"layer": 9, "feature": 9860, "explanation": "phrases related to technology and data processing", "community": 230900, "id": "9_9860"}, {"layer": 9, "feature": 9954, "explanation": "instances of legal and contractual terms", "community": 230994, "id": "9_9954"}, {"layer": 9, "feature": 11016, "explanation": "technical terms related to computing such as files, actions, responses, crashes, and connections", "community": 232054, "id": "9_11016"}, {"layer": 9, "feature": 11076, "explanation": "verbs related to forceful tearing or destruction", "community": 232114, "id": "9_11076"}, {"layer": 9, "feature": 12161, "explanation": "phrases related to light, energy absorption, and physical properties such as movement and speed", "community": 233197, "id": "9_12161"}, {"layer": 9, "feature": 12542, "explanation": "phrases relating to the passing of time", "community": 233578, "id": "9_12542"}, {"layer": 9, "feature": 13244, "explanation": "verbs related to actions or behaviors involving making a change or causing an effect", "community": 234280, "id": "9_13244"}, {"layer": 9, "feature": 13307, "explanation": "mentions of specific entities such as organizations, companies, and individuals", "community": 234342, "id": "9_13307"}, {"layer": 9, "feature": 13421, "explanation": "information related to terrorism and political figures", "community": 234456, "id": "9_13421"}, {"layer": 9, "feature": 13634, "explanation": "economic and policy-related terms", "community": 234669, "id": "9_13634"}, {"layer": 9, "feature": 13676, "explanation": "financial transactions and legal terms", "community": 234711, "id": "9_13676"}, {"layer": 9, "feature": 14274, "explanation": "terms related to social issues and conflicts", "community": 235308, "id": "9_14274"}, {"layer": 9, "feature": 14359, "explanation": "phrases related to specific substances or compounds, especially those related to health benefits", "community": 235393, "id": "9_14359"}, {"layer": 9, "feature": 15899, "explanation": "specific town names", "community": 236932, "id": "9_15899"}, {"layer": 9, "feature": 16463, "explanation": "actions involving physical exertion and movement", "community": 237496, "id": "9_16463"}, {"layer": 9, "feature": 16699, "explanation": "adjectives or phrases related to negative consequences", "community": 237732, "id": "9_16699"}, {"layer": 9, "feature": 17149, "explanation": "instructions or steps related to a specific process", "community": 238181, "id": "9_17149"}, {"layer": 9, "feature": 17299, "explanation": "phrases related to societal and political issues", "community": 238331, "id": "9_17299"}, {"layer": 9, "feature": 17714, "explanation": "terms related to different biological processes, such as protein secretion, genetic mutations, odor detection, and embryonic development", "community": 238746, "id": "9_17714"}, {"layer": 9, "feature": 19038, "explanation": "phrases related to misconduct or controversial actions", "community": 240069, "id": "9_19038"}, {"layer": 9, "feature": 20073, "explanation": "instructions or steps related to physical movements or actions", "community": 241102, "id": "9_20073"}, {"layer": 9, "feature": 20156, "explanation": "phrases related to the process of passing or accepting something, such as legislation or agreements", "community": 241185, "id": "9_20156"}, {"layer": 9, "feature": 21360, "explanation": "phrases related to lists or categories", "community": 242388, "id": "9_21360"}, {"layer": 9, "feature": 21375, "explanation": "negative or harmful words and phrases", "community": 242403, "id": "9_21375"}, {"layer": 9, "feature": 21522, "explanation": "safety guidelines related to physical spaces", "community": 242550, "id": "9_21522"}, {"layer": 9, "feature": 21698, "explanation": "terms related to technological processes and methodologies", "community": 242726, "id": "9_21698"}, {"layer": 9, "feature": 22987, "explanation": "phrases related to equality and comparison", "community": 244014, "id": "9_22987"}, {"layer": 9, "feature": 23192, "explanation": "words related to physical violence or conflict", "community": 244219, "id": "9_23192"}, {"layer": 9, "feature": 23450, "explanation": "phrases related to technology and development", "community": 244477, "id": "9_23450"}, {"layer": 9, "feature": 23692, "explanation": "references to ownership, property, and economic transactions", "community": 244717, "id": "9_23692"}, {"layer": 9, "feature": 23847, "explanation": "phrases related to taking action or making decisions", "community": 244872, "id": "9_23847"}, {"layer": 10, "feature": 520, "explanation": "words related to charitable actions or donations", "community": 246119, "id": "10_520"}, {"layer": 10, "feature": 588, "explanation": "words related to organizing or managing tasks and processes", "community": 246186, "id": "10_588"}, {"layer": 10, "feature": 1280, "explanation": "phrases related to control and manipulation", "community": 246876, "id": "10_1280"}, {"layer": 10, "feature": 1544, "explanation": "words related to legal actions and processes", "community": 247140, "id": "10_1544"}, {"layer": 10, "feature": 1796, "explanation": "verbs or nouns related to causing harm or damage", "community": 247392, "id": "10_1796"}, {"layer": 10, "feature": 2103, "explanation": "references to amounts of money or financial transactions", "community": 247699, "id": "10_2103"}, {"layer": 10, "feature": 2483, "explanation": "terms related to international relations and political policies", "community": 248079, "id": "10_2483"}, {"layer": 10, "feature": 4481, "explanation": " words related to scientific concepts or technical terms", "community": 250076, "id": "10_4481"}, {"layer": 10, "feature": 5285, "explanation": "instructions or recommendations for preventing particular issues such as moisture or injuries", "community": 250878, "id": "10_5285"}, {"layer": 10, "feature": 6708, "explanation": "terms related to legal and intellectual property issues", "community": 252298, "id": "10_6708"}, {"layer": 10, "feature": 6767, "explanation": "punctuation marks", "community": 252357, "id": "10_6767"}, {"layer": 10, "feature": 6783, "explanation": "proper nouns, likely names of individuals", "community": 252373, "id": "10_6783"}, {"layer": 10, "feature": 7013, "explanation": "words related to physical forces or actions like scraping, pushing, bending, pulling, leaking, pouring, cutting, clicking, sapping, bolstering, easing, shedding, and pumping", "community": 252603, "id": "10_7013"}, {"layer": 10, "feature": 7334, "explanation": "data and figures related to taxes", "community": 252924, "id": "10_7334"}, {"layer": 10, "feature": 8260, "explanation": "verbs related to activities or actions", "community": 253848, "id": "10_8260"}, {"layer": 10, "feature": 9276, "explanation": "terms related to politics and policies", "community": 254861, "id": "10_9276"}, {"layer": 10, "feature": 10755, "explanation": "economic and political terms related to government policies and regulations", "community": 256340, "id": "10_10755"}, {"layer": 10, "feature": 11364, "explanation": "legal and political terms, including dates and locations", "community": 256949, "id": "10_11364"}, {"layer": 10, "feature": 11501, "explanation": "mentions of ongoing or anticipated events and activities", "community": 257086, "id": "10_11501"}, {"layer": 10, "feature": 11917, "explanation": "information related to financial transactions and payments", "community": 257502, "id": "10_11917"}, {"layer": 10, "feature": 12144, "explanation": "instances of physical imperfections or issues", "community": 257728, "id": "10_12144"}, {"layer": 10, "feature": 14137, "explanation": "references to financial gain or profit", "community": 259719, "id": "10_14137"}, {"layer": 10, "feature": 14243, "explanation": "mentions of adjustments or alignments", "community": 259825, "id": "10_14243"}, {"layer": 10, "feature": 14609, "explanation": "ingredients and cooking instructions", "community": 260191, "id": "10_14609"}, {"layer": 10, "feature": 15146, "explanation": "words related to legal and governmental topics", "community": 260727, "id": "10_15146"}, {"layer": 10, "feature": 15981, "explanation": "instructions or steps in a process, especially related to heating, burning, or changing the physical state of a material", "community": 261562, "id": "10_15981"}, {"layer": 10, "feature": 16670, "explanation": "words related to actions or plans being put into effect", "community": 262251, "id": "10_16670"}, {"layer": 10, "feature": 17071, "explanation": "verbs related to strong actions of destruction or tearing", "community": 262651, "id": "10_17071"}, {"layer": 10, "feature": 17249, "explanation": "verbs or phrases related to actions and processes", "community": 262828, "id": "10_17249"}, {"layer": 10, "feature": 18453, "explanation": "detailed information and analyses related to media content", "community": 264029, "id": "10_18453"}, {"layer": 10, "feature": 18908, "explanation": "verbs related to actions or activities", "community": 264483, "id": "10_18908"}, {"layer": 10, "feature": 18915, "explanation": "information related to technology and infrastructure", "community": 264490, "id": "10_18915"}, {"layer": 10, "feature": 20104, "explanation": "terms related to financial aspects, specifically mentioning funding and capital", "community": 265677, "id": "10_20104"}, {"layer": 10, "feature": 20174, "explanation": "terms related to electricity and magnetic fields", "community": 265747, "id": "10_20174"}, {"layer": 10, "feature": 20597, "explanation": "verbs related to actions or tasks that involve others", "community": 266169, "id": "10_20597"}, {"layer": 10, "feature": 21141, "explanation": "references to political figures and related issues", "community": 266710, "id": "10_21141"}, {"layer": 10, "feature": 22200, "explanation": "terms related to analyzing and discussing various subjects, including legal, political, medical, and technological topics", "community": 267769, "id": "10_22200"}, {"layer": 10, "feature": 22389, "explanation": "words related to relationships between people or entities", "community": 267958, "id": "10_22389"}, {"layer": 10, "feature": 22809, "explanation": "words related to physical states or actions such as blending, permeating, obscuring, squeezing, filling, wrapping, compressing, deactivating, drowning, shredding, bathing, activating, burning, loosening, repairing", "community": 268378, "id": "10_22809"}, {"layer": 10, "feature": 22937, "explanation": "words related to the medical field and healthcare, specifically terms related to medical conditions, treatments, and health-related concepts", "community": 268506, "id": "10_22937"}, {"layer": 10, "feature": 23075, "explanation": "mentions of tear gas and related actions like firing, using, or being hit by tear gas", "community": 268643, "id": "10_23075"}, {"layer": 10, "feature": 23105, "explanation": "actions involving physical movement, such as sliding, pulling, pressing, pushing, and screwing", "community": 268673, "id": "10_23105"}, {"layer": 10, "feature": 23801, "explanation": "technical instructions or commands", "community": 269369, "id": "10_23801"}, {"layer": 10, "feature": 24500, "explanation": "historical events and dates", "community": 270068, "id": "10_24500"}, {"layer": 11, "feature": 414, "explanation": "legal and judicial terms and phrases", "community": 270558, "id": "11_414"}, {"layer": 11, "feature": 559, "explanation": "words related to actions or behaviors", "community": 270702, "id": "11_559"}, {"layer": 11, "feature": 932, "explanation": "comments and feedback related to product features and quality", "community": 271075, "id": "11_932"}, {"layer": 11, "feature": 1181, "explanation": "words related to equipment malfunctions and accidents", "community": 271324, "id": "11_1181"}, {"layer": 11, "feature": 1454, "explanation": "words related to fashion and style", "community": 271597, "id": "11_1454"}, {"layer": 11, "feature": 3920, "explanation": "phrases related to actions or changes happening in a process or sequence", "community": 274059, "id": "11_3920"}, {"layer": 11, "feature": 4569, "explanation": "names of American football teams", "community": 274708, "id": "11_4569"}, {"layer": 11, "feature": 4579, "explanation": "actions or processes involving physical interactions or forces", "community": 274718, "id": "11_4579"}, {"layer": 11, "feature": 5876, "explanation": "phrases related to instructions or procedures", "community": 276015, "id": "11_5876"}, {"layer": 11, "feature": 6053, "explanation": "phrases related to human rights principles and values", "community": 276192, "id": "11_6053"}, {"layer": 11, "feature": 6239, "explanation": "technical terms related to manufacturing, processing, and testing", "community": 276378, "id": "11_6239"}, {"layer": 11, "feature": 7095, "explanation": "specific terms related to research, development, and control in various contexts", "community": 277233, "id": "11_7095"}, {"layer": 11, "feature": 7748, "explanation": "references to technology-related terms and actions", "community": 277886, "id": "11_7748"}, {"layer": 11, "feature": 8029, "explanation": "medical terms related to different body parts, such as \"hockey sticks\", \"brains\", and \"ACL\"", "community": 278167, "id": "11_8029"}, {"layer": 11, "feature": 8669, "explanation": "words related to information organization and categorization", "community": 278807, "id": "11_8669"}, {"layer": 11, "feature": 9733, "explanation": "statements involving political figures and activities", "community": 279870, "id": "11_9733"}, {"layer": 11, "feature": 9943, "explanation": "references to different types of violence and harassment", "community": 280080, "id": "11_9943"}, {"layer": 11, "feature": 10419, "explanation": "countries and locations", "community": 280556, "id": "11_10419"}, {"layer": 11, "feature": 11360, "explanation": "verbs related to actions or processes", "community": 281496, "id": "11_11360"}, {"layer": 11, "feature": 11843, "explanation": "proper nouns or names", "community": 281979, "id": "11_11843"}, {"layer": 11, "feature": 12088, "explanation": "language related to software or technical aspects", "community": 282223, "id": "11_12088"}, {"layer": 11, "feature": 12539, "explanation": "words related to physical changes or processes, such as cooling, solidifying, melting, and oxidizing", "community": 282674, "id": "11_12539"}, {"layer": 11, "feature": 12895, "explanation": "information related to physical properties and characteristics, especially focusing on structural stability and loading", "community": 283030, "id": "11_12895"}, {"layer": 11, "feature": 13291, "explanation": "phrases related to physical destruction or violence", "community": 283426, "id": "11_13291"}, {"layer": 11, "feature": 14211, "explanation": "mentions of controversial topics or issues", "community": 284346, "id": "11_14211"}, {"layer": 11, "feature": 14764, "explanation": "words related to specific entities or topics, such as \"Interior\", \"Blood\", \"approach\", \"disc\", etc", "community": 284899, "id": "11_14764"}, {"layer": 11, "feature": 15191, "explanation": "technical terms related to physics and mechanics", "community": 285325, "id": "11_15191"}, {"layer": 11, "feature": 15378, "explanation": "consequences or results of actions or phenomena", "community": 285512, "id": "11_15378"}, {"layer": 11, "feature": 15790, "explanation": "phrases related to legal or criminal activities", "community": 285924, "id": "11_15790"}, {"layer": 11, "feature": 16250, "explanation": "specific actions or requirements stated in a formal or regulatory context", "community": 286384, "id": "11_16250"}, {"layer": 11, "feature": 16382, "explanation": "scientific and technical terms related to biology and medicine", "community": 286516, "id": "11_16382"}, {"layer": 11, "feature": 16442, "explanation": "instructions for preventing or solving issues related to specific objects or actions", "community": 286576, "id": "11_16442"}, {"layer": 11, "feature": 16663, "explanation": "mentions of transportation accidents, specifically crashes", "community": 286797, "id": "11_16663"}, {"layer": 11, "feature": 17013, "explanation": "words related to destruction and negative consequences", "community": 287146, "id": "11_17013"}, {"layer": 11, "feature": 17416, "explanation": "words related to amusement park rides", "community": 287548, "id": "11_17416"}, {"layer": 11, "feature": 17950, "explanation": "verbs related to actions or events", "community": 288081, "id": "11_17950"}, {"layer": 11, "feature": 19026, "explanation": "dates and events in history", "community": 289155, "id": "11_19026"}, {"layer": 11, "feature": 19420, "explanation": "actions related to cooking processes", "community": 289549, "id": "11_19420"}, {"layer": 11, "feature": 19955, "explanation": "phrases related to legal or official documents and processes", "community": 290082, "id": "11_19955"}, {"layer": 11, "feature": 19993, "explanation": "companies and organizations", "community": 290120, "id": "11_19993"}, {"layer": 11, "feature": 21493, "explanation": "references to accidents or incidents", "community": 291619, "id": "11_21493"}, {"layer": 11, "feature": 22355, "explanation": "phrases related to societal or ethical issues concerning various demographics and practices", "community": 292480, "id": "11_22355"}, {"layer": 11, "feature": 22590, "explanation": "keywords related to feedback, reports, and instructions", "community": 292714, "id": "11_22590"}, {"layer": 11, "feature": 23783, "explanation": "descriptions of materials used for protection or design", "community": 293905, "id": "11_23783"}, {"layer": 11, "feature": 24102, "explanation": "demographic information and actions related to military conflict", "community": 294223, "id": "11_24102"}, {"layer": 11, "feature": 24249, "explanation": "legalese terms and legal actions", "community": 294370, "id": "11_24249"}, {"layer": 11, "feature": 24260, "explanation": "instances of tear-related words", "community": 294381, "id": "11_24260"}, {"layer": 11, "feature": 24341, "explanation": "military combat related terms and actions", "community": 294462, "id": "11_24341"}, {"layer": 11, "feature": 24400, "explanation": "instances of punctuation marks, especially commas and special characters", "community": 294521, "id": "11_24400"}], "links": [{"similarity": 0.16073499619960785, "source": "0_3187", "target": "1_6831"}, {"similarity": 0.15189115703105927, "source": "0_3187", "target": "1_14479"}, {"similarity": 0.1998443603515625, "source": "0_9440", "target": "1_6831"}, {"similarity": 0.10521254688501358, "source": "0_9440", "target": "1_14479"}, {"similarity": 0.16522051393985748, "source": "0_9895", "target": "1_6831"}, {"similarity": 0.16805124282836914, "source": "0_9895", "target": "1_11587"}, {"similarity": 0.2544413208961487, "source": "0_9895", "target": "1_14479"}, {"similarity": 0.14595377445220947, "source": "0_9895", "target": "1_19865"}, {"similarity": 0.2008512020111084, "source": "0_12047", "target": "1_6831"}, {"similarity": 0.116424560546875, "source": "0_12047", "target": "1_11587"}, {"similarity": 0.207008957862854, "source": "0_12047", "target": "1_14479"}, {"similarity": 0.18883034586906433, "source": "1_6831", "target": "2_21401"}, {"similarity": 0.13887761533260345, "source": "1_11587", "target": "2_12727"}, {"similarity": 0.11444704234600067, "source": "1_11587", "target": "2_21401"}, {"similarity": 0.14002567529678345, "source": "1_14479", "target": "2_12727"}, {"similarity": 0.2006056010723114, "source": "1_14479", "target": "2_21401"}, {"similarity": 0.14496594667434692, "source": "2_12727", "target": "3_21861"}, {"similarity": 0.11925458908081055, "source": "2_12894", "target": "3_23093"}, {"similarity": 0.15002253651618958, "source": "2_21401", "target": "3_17242"}, {"similarity": 0.12292007356882095, "source": "2_21401", "target": "3_21861"}, {"similarity": 0.1240881010890007, "source": "3_23093", "target": "4_15235"}, {"similarity": 0.13001736998558044, "source": "5_10484", "target": "6_14853"}]}